{
  "name": "SteamGG",
  "downloads": [
    {
      "title": "Aarklash: Legacy Free Download (V612342)",
      "uploadDate": "2024-10-06T11:50:38+00:00",
      "fileSize": "",
      "uris": [
        "https://pixeldrain.com/u/Vnm1aqxV",
        "https://1fichier.com/?obr68jfwlcx78odttdjm",
        "https://buzzheavier.com/f/GRqFVVETwAA"
      ]
    },
    {
      "title": "Abalon Free Download",
      "uploadDate": "2024-10-06T11:50:40+00:00",
      "fileSize": "",
      "uris": [
        "https://pixeldrain.com/u/vK8MPmSm",
        "https://buzzheavier.com/f/GKfWYIoNgAA="
      ]
    },
    {
      "title": "Abandoned Souls Free Download",
      "uploadDate": "2024-10-06T11:50:42+00:00",
      "fileSize": "",
      "uris": [
        "https://pixeldrain.com/u/6FWZhLaX",
        "https://1fichier.com/?clmnh27kxsfo3362rtzm"
      ]
    },
    {
      "title": "Abiotic Factor Free Download (Crush Depth-v0.9.0.11281)",
      "uploadDate": "2024-10-06T11:50:44+00:00",
      "fileSize": "",
      "uris": [
        "https://akirabox.com/dkD3YqJw3LQK/file",
        "https://buzzheavier.com/f/GU5LWFVf0AA"
      ]
    },
    {
      "title": "Abnormal1999:Sector 49 Free Download",
      "uploadDate": "2024-10-06T11:50:46+00:00",
      "fileSize": "",
      "uris": [
        "https://buzzheavier.com/f/GTpJAxipAAA",
        "https://1fichier.com/?21ipd6is1orlejvkuy2g"
      ]
    },
    {
      "title": "Above Snakes Free Download (v1.4.5)",
      "uploadDate": "2024-10-06T11:50:50+00:00",
      "fileSize": "",
      "uris": ["https://pixeldrain.com/u/DgY1rxAx"]
    }
  ]
}